sklrean/__init__.py
sklrean/olafile.ipynb
skilean-0.0.5.dist-info/LICENSE
skilean-0.0.5.dist-info/METADATA
skilean-0.0.5.dist-info/WHEEL
skilean-0.0.5.dist-info/top_level.txt
skilean-0.0.5.dist-info/RECORD
