Metadata-Version: 2.2
Name: skilean
Version: 0.0.5
Summary: Python image processing library
Home-page: 
Author: Gaussian Kernal
Author-email: gaussiankernal@gmail.com
License: MIT
Requires-Python: >=2.7
License-File: LICENSE
Dynamic: author
Dynamic: author-email
Dynamic: license
Dynamic: requires-python
Dynamic: summary
